py_auth_amqp_wrapper/__init__.py
py_auth_amqp_wrapper/__main__.py
py_auth_amqp_wrapper/_getlogger.py
py_auth_amqp_wrapper/_load_config.py
py_auth_amqp_wrapper/_runner.py
py_auth_amqp_wrapper/_version.py
py_auth_amqp_wrapper-0.0.8.dist-info/LICENSE
py_auth_amqp_wrapper-0.0.8.dist-info/METADATA
py_auth_amqp_wrapper-0.0.8.dist-info/WHEEL
py_auth_amqp_wrapper-0.0.8.dist-info/top_level.txt
py_auth_amqp_wrapper-0.0.8.dist-info/RECORD
