Metadata-Version: 2.1
Name: py-auth-amqp-wrapper
Version: 0.0.8
Summary: A wrapper around pyjwt
Home-page: https://github.com/bad-microservices/py_auth_amqp_wrapper
Author: Ole Hannemann
Author-email: cerberus885@gmail.com
License: MIT
Keywords: AMQP
Classifier: Programming Language :: Python :: 3.0
Classifier: Programming Language :: Python :: 3.9
Classifier: License :: OSI Approved :: MIT License
Classifier: Development Status :: 3 - Alpha
Classifier: Topic :: Software Development :: Libraries :: Python Modules
Classifier: Intended Audience :: Developers
License-File: LICENSE
Requires-Dist: aio-pika
Requires-Dist: py-auth-micro
Requires-Dist: jwt-helper
Requires-Dist: amqp-helper
